{
  "bars_held_buckets": [
    {
      "avg_abs_entry_zscore": 2.818780235484874,
      "avg_bars_held": 1.0,
      "avg_cost_bps": 12.23137291592368,
      "avg_gross_pnl_bps": -12.68756507101938,
      "avg_net_pnl_bps": -24.918937986943064,
      "bucket": "1h",
      "gross_pnl_bps": -106727.79737741503,
      "gross_profit_factor": 0.8575967478057628,
      "hit_rate_gross": 0.5855920114122682,
      "net_pnl_bps": -209618.10634616506,
      "profit_outcome_rate": 0.5853542558250119,
      "stop_outcome_rate": 0.4139324774132192,
      "trade_count": 8412,
      "vertical_outcome_rate": 0.0007132667617689016
    },
    {
      "avg_abs_entry_zscore": 2.907320565532612,
      "avg_bars_held": 2.969142145414915,
      "avg_cost_bps": 12.690600076482951,
      "avg_gross_pnl_bps": 41.41516270794645,
      "avg_net_pnl_bps": 28.724562631463503,
      "bucket": "2-4h",
      "gross_pnl_bps": 1330047.9503657003,
      "gross_profit_factor": 2.2646692959071486,
      "hit_rate_gross": 0.770387669313405,
      "net_pnl_bps": 922489.3289094503,
      "profit_outcome_rate": 0.8043593336447143,
      "stop_outcome_rate": 0.07709792931651877,
      "trade_count": 32115,
      "vertical_outcome_rate": 0.11854273703876693
    },
    {
      "avg_abs_entry_zscore": 3.0549329912822527,
      "avg_bars_held": 6.409031443136193,
      "avg_cost_bps": 13.54896596686516,
      "avg_gross_pnl_bps": -54.32764283855247,
      "avg_net_pnl_bps": -67.87660880541765,
      "bucket": "5-12h",
      "gross_pnl_bps": -1204280.8588021926,
      "gross_profit_factor": 0.30664193974353265,
      "hit_rate_gross": 0.3810168268146344,
      "net_pnl_bps": -1504620.7873896929,
      "profit_outcome_rate": 0.563359949474444,
      "stop_outcome_rate": 0.02476654486398701,
      "trade_count": 22167,
      "vertical_outcome_rate": 0.411873505661569
    },
    {
      "avg_abs_entry_zscore": 3.927420165742104,
      "avg_bars_held": 14.11413043478261,
      "avg_cost_bps": 15.420117051630434,
      "avg_gross_pnl_bps": -365.6919630821157,
      "avg_net_pnl_bps": -381.1120801337461,
      "bucket": "13-24h",
      "gross_pnl_bps": -67287.32120710929,
      "gross_profit_factor": 0.002820406266753231,
      "hit_rate_gross": 0.021739130434782608,
      "net_pnl_bps": -70124.62274460928,
      "profit_outcome_rate": 0.5597826086956522,
      "stop_outcome_rate": 0.010869565217391304,
      "trade_count": 184,
      "vertical_outcome_rate": 0.42934782608695654
    },
    {
      "avg_abs_entry_zscore": null,
      "avg_bars_held": null,
      "avg_cost_bps": null,
      "avg_gross_pnl_bps": null,
      "avg_net_pnl_bps": null,
      "bucket": "25h+",
      "gross_pnl_bps": 0.0,
      "gross_profit_factor": null,
      "hit_rate_gross": null,
      "net_pnl_bps": 0.0,
      "profit_outcome_rate": null,
      "stop_outcome_rate": null,
      "trade_count": 0,
      "vertical_outcome_rate": null
    }
  ],
  "bottom_gross_pairs": [
    {
      "avg_abs_entry_zscore": 2.907291996522837,
      "avg_bars_held": 4.0638297872340425,
      "avg_cost_bps": 13.01595744680851,
      "avg_gross_pnl_bps": -4.816151486698096,
      "avg_net_pnl_bps": -17.832108933506603,
      "bucket": "AVAXUSDT/ETCUSDT",
      "gross_pnl_bps": -7696.210075743556,
      "gross_profit_factor": 0.9302281479914883,
      "hit_rate_gross": 0.6151439299123905,
      "net_pnl_bps": -28495.710075743555,
      "profit_outcome_rate": 0.7021276595744681,
      "stop_outcome_rate": 0.10450563204005006,
      "trade_count": 1598,
      "vertical_outcome_rate": 0.19336670838548184
    },
    {
      "avg_abs_entry_zscore": 2.961235058476163,
      "avg_bars_held": 4.667721518987341,
      "avg_cost_bps": 13.166930379746836,
      "avg_gross_pnl_bps": -7.017949609097547,
      "avg_net_pnl_bps": -20.184879988844386,
      "bucket": "ETCUSDT/OPUSDT",
      "gross_pnl_bps": -11088.360382374125,
      "gross_profit_factor": 0.8945572988894883,
      "hit_rate_gross": 0.5905063291139241,
      "net_pnl_bps": -31892.11038237413,
      "profit_outcome_rate": 0.6481012658227848,
      "stop_outcome_rate": 0.1360759493670886,
      "trade_count": 1580,
      "vertical_outcome_rate": 0.2158227848101266
    },
    {
      "avg_abs_entry_zscore": 2.9581303499024116,
      "avg_bars_held": 2.5734989648033126,
      "avg_cost_bps": 12.544809730848861,
      "avg_gross_pnl_bps": -7.046586915452716,
      "avg_net_pnl_bps": -19.59139664630158,
      "bucket": "AVAXUSDT/ETHUSDT",
      "gross_pnl_bps": -10210.504440490986,
      "gross_profit_factor": 0.8806716426941493,
      "hit_rate_gross": 0.587991718426501,
      "net_pnl_bps": -28387.933740490986,
      "profit_outcome_rate": 0.6549344375431332,
      "stop_outcome_rate": 0.08281573498964803,
      "trade_count": 1449,
      "vertical_outcome_rate": 0.26224982746721875
    },
    {
      "avg_abs_entry_zscore": 2.873590906734882,
      "avg_bars_held": 4.656189865298268,
      "avg_cost_bps": 13.164047466324567,
      "avg_gross_pnl_bps": -7.078476043357573,
      "avg_net_pnl_bps": -20.242523509682137,
      "bucket": "ADAUSDT/ATOMUSDT",
      "gross_pnl_bps": -11035.344151594456,
      "gross_profit_factor": 0.8941035850603387,
      "hit_rate_gross": 0.5881975625400898,
      "net_pnl_bps": -31558.09415159445,
      "profit_outcome_rate": 0.6856959589480436,
      "stop_outcome_rate": 0.10968569595894805,
      "trade_count": 1559,
      "vertical_outcome_rate": 0.20461834509300833
    },
    {
      "avg_abs_entry_zscore": 3.0341632849121734,
      "avg_bars_held": 3.5705920624593364,
      "avg_cost_bps": 12.6968903057905,
      "avg_gross_pnl_bps": -7.3188009316646125,
      "avg_net_pnl_bps": -20.015691237455112,
      "bucket": "ETHUSDT/SOLUSDT",
      "gross_pnl_bps": -11248.997031968509,
      "gross_profit_factor": 0.8387005865578114,
      "hit_rate_gross": 0.5712426805465192,
      "net_pnl_bps": -30764.11743196851,
      "profit_outcome_rate": 0.6636304489264802,
      "stop_outcome_rate": 0.0826284970722186,
      "trade_count": 1537,
      "vertical_outcome_rate": 0.25374105400130126
    },
    {
      "avg_abs_entry_zscore": 2.931366656258328,
      "avg_bars_held": 5.307405102675793,
      "avg_cost_bps": 13.123577660236466,
      "avg_gross_pnl_bps": -10.926697671319289,
      "avg_net_pnl_bps": -24.050275331555753,
      "bucket": "ETHUSDT/OPUSDT",
      "gross_pnl_bps": -17559.203157810098,
      "gross_profit_factor": 0.8108190261037179,
      "hit_rate_gross": 0.5544492843808339,
      "net_pnl_bps": -38648.792457810094,
      "profit_outcome_rate": 0.6645924082140635,
      "stop_outcome_rate": 0.10827629122588675,
      "trade_count": 1607,
      "vertical_outcome_rate": 0.2271313005600498
    },
    {
      "avg_abs_entry_zscore": 2.9193581395758215,
      "avg_bars_held": 4.7786211258697024,
      "avg_cost_bps": 13.194655281467426,
      "avg_gross_pnl_bps": -12.67614848782701,
      "avg_net_pnl_bps": -25.870803769294433,
      "bucket": "ADAUSDT/ARBUSDT",
      "gross_pnl_bps": -20040.990759254502,
      "gross_profit_factor": 0.8260926711719283,
      "hit_rate_gross": 0.5774826059456041,
      "net_pnl_bps": -40901.7407592545,
      "profit_outcome_rate": 0.6793168880455408,
      "stop_outcome_rate": 0.13345983554712207,
      "trade_count": 1581,
      "vertical_outcome_rate": 0.18722327640733713
    },
    {
      "avg_abs_entry_zscore": 2.9193028914634165,
      "avg_bars_held": 4.918287937743191,
      "avg_cost_bps": 13.229571984435797,
      "avg_gross_pnl_bps": -14.76679529390889,
      "avg_net_pnl_bps": -27.996367278344685,
      "bucket": "DOTUSDT/OPUSDT",
      "gross_pnl_bps": -22770.398343207507,
      "gross_profit_factor": 0.7999367806127816,
      "hit_rate_gross": 0.5933852140077821,
      "net_pnl_bps": -43170.398343207504,
      "profit_outcome_rate": 0.6997405966277561,
      "stop_outcome_rate": 0.12710765239948119,
      "trade_count": 1542,
      "vertical_outcome_rate": 0.17315175097276264
    },
    {
      "avg_abs_entry_zscore": 2.9073502208084845,
      "avg_bars_held": 5.036375239310785,
      "avg_cost_bps": 13.259093809827696,
      "avg_gross_pnl_bps": -15.512493031921219,
      "avg_net_pnl_bps": -28.77158684174892,
      "bucket": "ADAUSDT/XRPUSDT",
      "gross_pnl_bps": -24308.07658102055,
      "gross_profit_factor": 0.8061524961666481,
      "hit_rate_gross": 0.5909380982769623,
      "net_pnl_bps": -45085.076581020556,
      "profit_outcome_rate": 0.6790044671346522,
      "stop_outcome_rate": 0.12699425654116145,
      "trade_count": 1567,
      "vertical_outcome_rate": 0.19400127632418634
    },
    {
      "avg_abs_entry_zscore": 2.956010220436595,
      "avg_bars_held": 4.628272251308901,
      "avg_cost_bps": 12.979805235602091,
      "avg_gross_pnl_bps": -17.133045608224197,
      "avg_net_pnl_bps": -30.11285084382629,
      "bucket": "ETHUSDT/LINKUSDT",
      "gross_pnl_bps": -26179.293689366576,
      "gross_profit_factor": 0.6723341680152952,
      "hit_rate_gross": 0.5484293193717278,
      "net_pnl_bps": -46012.43608936657,
      "profit_outcome_rate": 0.6341623036649214,
      "stop_outcome_rate": 0.10863874345549739,
      "trade_count": 1528,
      "vertical_outcome_rate": 0.25719895287958117
    }
  ],
  "diagnosis": {
    "notes": [
      "O edge bruto agregado e nao-positivo antes de custos.",
      "PROFIT ocorre pelo menos tao frequentemente quanto STOP; foco deve ser payoff medio.",
      "|z| >= 3.0 nao melhora o gross medio contra a faixa 2.0-2.5.",
      "O edge bruto aparece em reversoes de 2-4h e desaparece em holds de 5h+.",
      "Holds de 13-24h sao poucos, mas extremamente negativos em gross PnL medio.",
      "Lado com melhor gross medio: LONG_SPREAD (0.7236 bps/trade); pior: SHORT_SPREAD (-2.0391 bps/trade)."
    ],
    "recommendations": [
      "Priorizar mudanca no criterio de entrada antes de otimizar custo.",
      "Nao priorizar aumento simples de |z|; validar filtro de regime/velocidade.",
      "TASK-SIG-002 deve testar cap vertical <=4h como experimento causal, sem tocar em execucao.",
      "Gate por OU half-life curto e hipotese secundaria: exige registrar ou recalcular half-life por entrada antes de concluir."
    ]
  },
  "entry_zscore_buckets": [
    {
      "avg_abs_entry_zscore": 2.220437624511452,
      "avg_bars_held": 3.8024210094378335,
      "avg_cost_bps": 12.906101942278758,
      "avg_gross_pnl_bps": 1.5514238959779107,
      "avg_net_pnl_bps": -11.354678046300847,
      "bucket": "2.0-2.5",
      "gross_pnl_bps": 45369.840413978025,
      "gross_profit_factor": 1.0330656136928789,
      "hit_rate_gross": 0.6131856107235673,
      "net_pnl_bps": -332056.20478602196,
      "profit_outcome_rate": 0.6916974422103679,
      "stop_outcome_rate": 0.10576528518670497,
      "trade_count": 29244,
      "vertical_outcome_rate": 0.2025372726029271
    },
    {
      "avg_abs_entry_zscore": 2.7220758409023795,
      "avg_bars_held": 3.880159228996438,
      "avg_cost_bps": 12.922816884908165,
      "avg_gross_pnl_bps": 1.0613823898316754,
      "avg_net_pnl_bps": -11.86143449507649,
      "bucket": "2.5-3.0",
      "gross_pnl_bps": 15197.93443999976,
      "gross_profit_factor": 1.019611202322291,
      "hit_rate_gross": 0.6091905859347719,
      "net_pnl_bps": -169843.88053500024,
      "profit_outcome_rate": 0.680913471611146,
      "stop_outcome_rate": 0.1095746909700398,
      "trade_count": 14319,
      "vertical_outcome_rate": 0.20951183741881416
    },
    {
      "avg_abs_entry_zscore": 4.225195049139776,
      "avg_bars_held": 4.228527051514367,
      "avg_cost_bps": 13.003277265078953,
      "avg_gross_pnl_bps": -5.6337458904993305,
      "avg_net_pnl_bps": -18.637023155578284,
      "bucket": "3.0+",
      "gross_pnl_bps": -108815.80187499456,
      "gross_profit_factor": 0.9253896212836137,
      "hit_rate_gross": 0.5934247993787212,
      "net_pnl_bps": -359974.1022499945,
      "profit_outcome_rate": 0.69215635516438,
      "stop_outcome_rate": 0.09562516179135387,
      "trade_count": 19315,
      "vertical_outcome_rate": 0.2122184830442661
    }
  ],
  "generated_at_utc": "2026-07-03T13:00:21.081778+00:00",
  "input_json": "/home/arthur/Downloads/crypto-pair-trading/data/research/binance_public/cost_pilot/sprint8_canonical_backtest_results.json",
  "outcome_distribution": [
    {
      "avg_abs_entry_zscore": 2.956098275819969,
      "avg_bars_held": 3.6842226682354027,
      "avg_cost_bps": 12.8778885825432,
      "avg_gross_pnl_bps": 69.68568328497999,
      "avg_net_pnl_bps": 56.807794702436794,
      "bucket": "PROFIT",
      "gross_pnl_bps": 3020665.3133540275,
      "gross_profit_factor": 7.0800382143796226,
      "hit_rate_gross": 0.8442337416660899,
      "net_pnl_bps": 2462447.4769665278,
      "profit_outcome_rate": 1.0,
      "stop_outcome_rate": 0.0,
      "trade_count": 43347,
      "vertical_outcome_rate": 0.0
    },
    {
      "avg_abs_entry_zscore": 2.855006271940179,
      "avg_bars_held": 2.0474727300660622,
      "avg_cost_bps": 12.489277099016745,
      "avg_gross_pnl_bps": -260.5494586998394,
      "avg_net_pnl_bps": -273.0387357988562,
      "bucket": "STOP",
      "gross_pnl_bps": -1695916.426677255,
      "gross_profit_factor": 0.0,
      "hit_rate_gross": 0.0,
      "net_pnl_bps": -1777209.131314755,
      "profit_outcome_rate": 0.0,
      "stop_outcome_rate": 1.0,
      "trade_count": 6509,
      "vertical_outcome_rate": 0.0
    },
    {
      "avg_abs_entry_zscore": 2.979595795208265,
      "avg_bars_held": 5.790585163569344,
      "avg_cost_bps": 13.37088154853325,
      "avg_gross_pnl_bps": -105.43671584225076,
      "avg_net_pnl_bps": -118.807597390784,
      "bucket": "VERTICAL",
      "gross_pnl_bps": -1372996.9136977894,
      "gross_profit_factor": 0.02817186413027501,
      "hit_rate_gross": 0.11687912763016434,
      "net_pnl_bps": -1547112.5332227892,
      "profit_outcome_rate": 0.0,
      "stop_outcome_rate": 0.0,
      "trade_count": 13022,
      "vertical_outcome_rate": 1.0
    }
  ],
  "overall": {
    "avg_abs_entry_zscore": 2.9504997651202145,
    "avg_bars_held": 3.9510162536976368,
    "avg_cost_bps": 12.93975890693088,
    "avg_gross_pnl_bps": -0.7673276348009919,
    "avg_net_pnl_bps": -13.707086541731874,
    "gross_pnl_bps": -48248.027021016766,
    "gross_profit_factor": 0.9866183309308325,
    "hit_rate_gross": 0.606205668119215,
    "net_pnl_bps": -861874.1875710167,
    "profit_outcome_rate": 0.6893826139508255,
    "stop_outcome_rate": 0.10351792359807882,
    "trade_count": 62878,
    "vertical_outcome_rate": 0.20709946245109578
  },
  "pair_count": 41,
  "pair_summary": [
    {
      "avg_abs_entry_zscore": 2.987824338236814,
      "avg_bars_held": 3.2116585704371965,
      "avg_cost_bps": 12.780493251214436,
      "avg_gross_pnl_bps": 10.760693774039392,
      "avg_net_pnl_bps": -2.019799477175043,
      "bucket": "ETCUSDT/LTCUSDT",
      "gross_pnl_bps": 15506.159728390765,
      "gross_profit_factor": 1.2373885129038764,
      "hit_rate_gross": 0.6391394864677308,
      "net_pnl_bps": -2910.531046609237,
      "profit_outcome_rate": 0.6613462873004857,
      "stop_outcome_rate": 0.08605135322692574,
      "trade_count": 1441,
      "vertical_outcome_rate": 0.25260235947258847
    },
    {
      "avg_abs_entry_zscore": 2.836694221137136,
      "avg_bars_held": 4.497797356828194,
      "avg_cost_bps": 13.124449339207048,
      "avg_gross_pnl_bps": 9.022161129354068,
      "avg_net_pnl_bps": -4.10228820985298,
      "bucket": "AVAXUSDT/DOTUSDT",
      "gross_pnl_bps": 14336.214034543613,
      "gross_profit_factor": 1.1598021746045348,
      "hit_rate_gross": 0.6337319068596602,
      "net_pnl_bps": -6518.535965456385,
      "profit_outcome_rate": 0.7035871617369415,
      "stop_outcome_rate": 0.10258023914411579,
      "trade_count": 1589,
      "vertical_outcome_rate": 0.19383259911894274
    },
    {
      "avg_abs_entry_zscore": 2.8834858614155796,
      "avg_bars_held": 4.7902408111533585,
      "avg_cost_bps": 13.19756020278834,
      "avg_gross_pnl_bps": 8.679069943074984,
      "avg_net_pnl_bps": -4.518490259713356,
      "bucket": "ARBUSDT/OPUSDT",
      "gross_pnl_bps": 13695.572370172325,
      "gross_profit_factor": 1.159321074656414,
      "hit_rate_gross": 0.6166032953105196,
      "net_pnl_bps": -7130.1776298276745,
      "profit_outcome_rate": 0.6977186311787072,
      "stop_outcome_rate": 0.10202788339670468,
      "trade_count": 1578,
      "vertical_outcome_rate": 0.2002534854245881
    },
    {
      "avg_abs_entry_zscore": 2.857530247487126,
      "avg_bars_held": 4.573613766730402,
      "avg_cost_bps": 13.1434034416826,
      "avg_gross_pnl_bps": 8.563050089263152,
      "avg_net_pnl_bps": -4.580353352419448,
      "bucket": "ADAUSDT/DOTUSDT",
      "gross_pnl_bps": 13435.425590053885,
      "gross_profit_factor": 1.1654214287004483,
      "hit_rate_gross": 0.6175908221797323,
      "net_pnl_bps": -7186.574409946114,
      "profit_outcome_rate": 0.715742511153601,
      "stop_outcome_rate": 0.09369024856596558,
      "trade_count": 1569,
      "vertical_outcome_rate": 0.1905672402804334
    },
    {
      "avg_abs_entry_zscore": 2.8913769140754826,
      "avg_bars_held": 4.484713375796178,
      "avg_cost_bps": 13.121178343949044,
      "avg_gross_pnl_bps": 8.47997480996526,
      "avg_net_pnl_bps": -4.641203533983783,
      "bucket": "ARBUSDT/ATOMUSDT",
      "gross_pnl_bps": 13313.560451645459,
      "gross_profit_factor": 1.131861187155258,
      "hit_rate_gross": 0.6070063694267516,
      "net_pnl_bps": -7286.68954835454,
      "profit_outcome_rate": 0.7114649681528662,
      "stop_outcome_rate": 0.12165605095541401,
      "trade_count": 1570,
      "vertical_outcome_rate": 0.16687898089171974
    },
    {
      "avg_abs_entry_zscore": 2.9648829261591003,
      "avg_bars_held": 3.9654947916666665,
      "avg_cost_bps": 12.991373697916666,
      "avg_gross_pnl_bps": 8.468239939784217,
      "avg_net_pnl_bps": -4.523133758132448,
      "bucket": "ARBUSDT/ETCUSDT",
      "gross_pnl_bps": 13007.216547508557,
      "gross_profit_factor": 1.1433366465066794,
      "hit_rate_gross": 0.6204427083333334,
      "net_pnl_bps": -6947.533452491441,
      "profit_outcome_rate": 0.6985677083333334,
      "stop_outcome_rate": 0.10611979166666667,
      "trade_count": 1536,
      "vertical_outcome_rate": 0.1953125
    },
    {
      "avg_abs_entry_zscore": 3.0722743654284326,
      "avg_bars_held": 3.8105867346938775,
      "avg_cost_bps": 12.925115194515307,
      "avg_gross_pnl_bps": 7.263314477602812,
      "avg_net_pnl_bps": -5.661800716912492,
      "bucket": "DOGEUSDT/ETCUSDT",
      "gross_pnl_bps": 11388.87710088121,
      "gross_profit_factor": 1.1163118837332997,
      "hit_rate_gross": 0.6320153061224489,
      "net_pnl_bps": -8877.703524118788,
      "profit_outcome_rate": 0.6964285714285714,
      "stop_outcome_rate": 0.10522959183673469,
      "trade_count": 1568,
      "vertical_outcome_rate": 0.19834183673469388
    },
    {
      "avg_abs_entry_zscore": 2.9896181583914587,
      "avg_bars_held": 4.406423718344657,
      "avg_cost_bps": 13.069769518221126,
      "avg_gross_pnl_bps": 7.236557070049314,
      "avg_net_pnl_bps": -5.833212448171807,
      "bucket": "DOGEUSDT/DOTUSDT",
      "gross_pnl_bps": 11715.98589640984,
      "gross_profit_factor": 1.1088720182584149,
      "hit_rate_gross": 0.6287831995058678,
      "net_pnl_bps": -9443.970953590155,
      "profit_outcome_rate": 0.7103150092649784,
      "stop_outcome_rate": 0.11982705373687462,
      "trade_count": 1619,
      "vertical_outcome_rate": 0.169857936998147
    },
    {
      "avg_abs_entry_zscore": 2.8341085231965897,
      "avg_bars_held": 4.542664211172498,
      "avg_cost_bps": 13.135666052793125,
      "avg_gross_pnl_bps": 4.93067724146818,
      "avg_net_pnl_bps": -8.204988811324945,
      "bucket": "ATOMUSDT/DOTUSDT",
      "gross_pnl_bps": 8032.073226351665,
      "gross_profit_factor": 1.1006086262152561,
      "hit_rate_gross": 0.6193984039287906,
      "net_pnl_bps": -13365.926773648334,
      "profit_outcome_rate": 0.6942909760589319,
      "stop_outcome_rate": 0.1092694904849601,
      "trade_count": 1629,
      "vertical_outcome_rate": 0.19643953345610804
    },
    {
      "avg_abs_entry_zscore": 2.9289988266451275,
      "avg_bars_held": 4.547099189020586,
      "avg_cost_bps": 13.136774797255146,
      "avg_gross_pnl_bps": 4.347401749392494,
      "avg_net_pnl_bps": -8.78937304786265,
      "bucket": "ARBUSDT/DOTUSDT",
      "gross_pnl_bps": 6968.885004276169,
      "gross_profit_factor": 1.068496420573064,
      "hit_rate_gross": 0.6138490330630069,
      "net_pnl_bps": -14089.364995723829,
      "profit_outcome_rate": 0.7105427323767936,
      "stop_outcome_rate": 0.11977542108546475,
      "trade_count": 1603,
      "vertical_outcome_rate": 0.16968184653774174
    },
    {
      "avg_abs_entry_zscore": 3.1463049144566693,
      "avg_bars_held": 2.457044673539519,
      "avg_cost_bps": 12.502404209621991,
      "avg_gross_pnl_bps": 3.5307014096255767,
      "avg_net_pnl_bps": -8.971702799996418,
      "bucket": "DOGEUSDT/ETHUSDT",
      "gross_pnl_bps": 5137.170551005214,
      "gross_profit_factor": 1.0658632815769336,
      "hit_rate_gross": 0.6123711340206186,
      "net_pnl_bps": -13053.82757399479,
      "profit_outcome_rate": 0.668041237113402,
      "stop_outcome_rate": 0.08247422680412371,
      "trade_count": 1455,
      "vertical_outcome_rate": 0.24948453608247423
    },
    {
      "avg_abs_entry_zscore": 2.873864336679,
      "avg_bars_held": 3.841309823677582,
      "avg_cost_bps": 12.960327455919396,
      "avg_gross_pnl_bps": 3.2341416092733453,
      "avg_net_pnl_bps": -9.726185846646048,
      "bucket": "ATOMUSDT/ETCUSDT",
      "gross_pnl_bps": 5135.816875526072,
      "gross_profit_factor": 1.059879856463367,
      "hit_rate_gross": 0.6032745591939547,
      "net_pnl_bps": -15445.183124473926,
      "profit_outcome_rate": 0.6857682619647355,
      "stop_outcome_rate": 0.12027707808564232,
      "trade_count": 1588,
      "vertical_outcome_rate": 0.19395465994962216
    },
    {
      "avg_abs_entry_zscore": 2.9073748830472668,
      "avg_bars_held": 4.110599078341014,
      "avg_cost_bps": 13.027649769585253,
      "avg_gross_pnl_bps": 3.2251504206909725,
      "avg_net_pnl_bps": -9.80249934889428,
      "bucket": "DOTUSDT/LINKUSDT",
      "gross_pnl_bps": 4899.003489029587,
      "gross_profit_factor": 1.0603842162049673,
      "hit_rate_gross": 0.6267281105990783,
      "net_pnl_bps": -14889.996510970412,
      "profit_outcome_rate": 0.717577353522054,
      "stop_outcome_rate": 0.09809084924292298,
      "trade_count": 1519,
      "vertical_outcome_rate": 0.18433179723502305
    },
    {
      "avg_abs_entry_zscore": 2.9423601615501447,
      "avg_bars_held": 3.3712168004941323,
      "avg_cost_bps": 12.645208755404571,
      "avg_gross_pnl_bps": 1.6867825568948043,
      "avg_net_pnl_bps": -10.958426198509766,
      "bucket": "BTCUSDT/SOLUSDT",
      "gross_pnl_bps": 2730.900959612688,
      "gross_profit_factor": 1.0588427322888792,
      "hit_rate_gross": 0.6016059295861643,
      "net_pnl_bps": -17741.69201538731,
      "profit_outcome_rate": 0.692402717726992,
      "stop_outcome_rate": 0.08400247066090179,
      "trade_count": 1619,
      "vertical_outcome_rate": 0.22359481161210623
    },
    {
      "avg_abs_entry_zscore": 3.0645077761682544,
      "avg_bars_held": 2.374285714285714,
      "avg_cost_bps": 12.502636285714283,
      "avg_gross_pnl_bps": 1.3603490022094697,
      "avg_net_pnl_bps": -11.142287283504816,
      "bucket": "ETCUSDT/ETHUSDT",
      "gross_pnl_bps": 1904.4886030932576,
      "gross_profit_factor": 1.0311669618578159,
      "hit_rate_gross": 0.6242857142857143,
      "net_pnl_bps": -15599.202196906743,
      "profit_outcome_rate": 0.6628571428571428,
      "stop_outcome_rate": 0.07214285714285715,
      "trade_count": 1400,
      "vertical_outcome_rate": 0.265
    },
    {
      "avg_abs_entry_zscore": 3.061888517403435,
      "avg_bars_held": 2.591204037490988,
      "avg_cost_bps": 12.548557894736842,
      "avg_gross_pnl_bps": 1.2112490564473746,
      "avg_net_pnl_bps": -11.33730883828947,
      "bucket": "ARBUSDT/ETHUSDT",
      "gross_pnl_bps": 1680.0024412925086,
      "gross_profit_factor": 1.0238144641246492,
      "hit_rate_gross": 0.608507570295602,
      "net_pnl_bps": -15724.847358707495,
      "profit_outcome_rate": 0.7007930785868781,
      "stop_outcome_rate": 0.06488824801730353,
      "trade_count": 1387,
      "vertical_outcome_rate": 0.2343186733958183
    },
    {
      "avg_abs_entry_zscore": 2.9985605532349258,
      "avg_bars_held": 2.4778699861687414,
      "avg_cost_bps": 12.524565076071921,
      "avg_gross_pnl_bps": 0.4570601724184357,
      "avg_net_pnl_bps": -12.067504903653488,
      "bucket": "ADAUSDT/ETHUSDT",
      "gross_pnl_bps": 660.909009317058,
      "gross_profit_factor": 1.0089781059893197,
      "hit_rate_gross": 0.6078838174273858,
      "net_pnl_bps": -17449.612090682942,
      "profit_outcome_rate": 0.6846473029045643,
      "stop_outcome_rate": 0.07676348547717843,
      "trade_count": 1446,
      "vertical_outcome_rate": 0.23858921161825727
    },
    {
      "avg_abs_entry_zscore": 2.9537741339784698,
      "avg_bars_held": 3.391123439667129,
      "avg_cost_bps": 12.791742545076284,
      "avg_gross_pnl_bps": 0.16021511941112446,
      "avg_net_pnl_bps": -12.631527425665157,
      "bucket": "AVAXUSDT/SOLUSDT",
      "gross_pnl_bps": 231.03020219084146,
      "gross_profit_factor": 1.002738600166609,
      "hit_rate_gross": 0.6171983356449375,
      "net_pnl_bps": -18214.662547809156,
      "profit_outcome_rate": 0.7122052704576977,
      "stop_outcome_rate": 0.09084604715672677,
      "trade_count": 1442,
      "vertical_outcome_rate": 0.19694868238557559
    },
    {
      "avg_abs_entry_zscore": 2.9989484294273137,
      "avg_bars_held": 2.610431423052157,
      "avg_cost_bps": 12.442761799742435,
      "avg_gross_pnl_bps": 0.09176028585208593,
      "avg_net_pnl_bps": -12.351001513890347,
      "bucket": "BTCUSDT/ETHUSDT",
      "gross_pnl_bps": 142.50372392828945,
      "gross_profit_factor": 1.003789466914087,
      "hit_rate_gross": 0.5911139729555699,
      "net_pnl_bps": -19181.10535107171,
      "profit_outcome_rate": 0.6851255634256278,
      "stop_outcome_rate": 0.06310367031551835,
      "trade_count": 1553,
      "vertical_outcome_rate": 0.2517707662588538
    },
    {
      "avg_abs_entry_zscore": 2.8829846563220793,
      "avg_bars_held": 4.219751471550032,
      "avg_cost_bps": 13.054937867887508,
      "avg_gross_pnl_bps": -0.17929349961911895,
      "avg_net_pnl_bps": -13.234231367506625,
      "bucket": "AVAXUSDT/LINKUSDT",
      "gross_pnl_bps": -274.1397609176329,
      "gross_profit_factor": 0.997096411967347,
      "hit_rate_gross": 0.6010464355788097,
      "net_pnl_bps": -20235.13976091763,
      "profit_outcome_rate": 0.7076520601700458,
      "stop_outcome_rate": 0.10987573577501634,
      "trade_count": 1529,
      "vertical_outcome_rate": 0.18247220405493786
    },
    {
      "avg_abs_entry_zscore": 2.984710336289435,
      "avg_bars_held": 3.9568345323741005,
      "avg_cost_bps": 12.989208633093526,
      "avg_gross_pnl_bps": -0.27030043875796655,
      "avg_net_pnl_bps": -13.259509071851491,
      "bucket": "ETCUSDT/LINKUSDT",
      "gross_pnl_bps": -413.28937086093083,
      "gross_profit_factor": 0.9953270205375598,
      "hit_rate_gross": 0.6206671026814912,
      "net_pnl_bps": -20273.78937086093,
      "profit_outcome_rate": 0.6873773708306082,
      "stop_outcome_rate": 0.12295618051013735,
      "trade_count": 1529,
      "vertical_outcome_rate": 0.18966644865925442
    },
    {
      "avg_abs_entry_zscore": 2.922557551923943,
      "avg_bars_held": 3.8603133159268928,
      "avg_cost_bps": 12.965078328981724,
      "avg_gross_pnl_bps": -0.34785629082915753,
      "avg_net_pnl_bps": -13.312934619810882,
      "bucket": "ADAUSDT/AVAXUSDT",
      "gross_pnl_bps": -532.9158375502693,
      "gross_profit_factor": 0.9940618227004601,
      "hit_rate_gross": 0.6096605744125326,
      "net_pnl_bps": -20395.41583755027,
      "profit_outcome_rate": 0.6932114882506527,
      "stop_outcome_rate": 0.1077023498694517,
      "trade_count": 1532,
      "vertical_outcome_rate": 0.19908616187989556
    },
    {
      "avg_abs_entry_zscore": 2.956823341932406,
      "avg_bars_held": 3.876,
      "avg_cost_bps": 12.969,
      "avg_gross_pnl_bps": -0.396087543908885,
      "avg_net_pnl_bps": -13.365087543908885,
      "bucket": "DOTUSDT/ETCUSDT",
      "gross_pnl_bps": -594.1313158633275,
      "gross_profit_factor": 0.9928047677974107,
      "hit_rate_gross": 0.6126666666666667,
      "net_pnl_bps": -20047.631315863327,
      "profit_outcome_rate": 0.6906666666666667,
      "stop_outcome_rate": 0.11333333333333333,
      "trade_count": 1500,
      "vertical_outcome_rate": 0.196
    },
    {
      "avg_abs_entry_zscore": 2.945668949032554,
      "avg_bars_held": 3.7879767291531996,
      "avg_cost_bps": 12.9469941822883,
      "avg_gross_pnl_bps": -0.8551432432215508,
      "avg_net_pnl_bps": -13.802137425509853,
      "bucket": "ADAUSDT/ETCUSDT",
      "gross_pnl_bps": -1322.906597263739,
      "gross_profit_factor": 0.9859305194774597,
      "hit_rate_gross": 0.632191338073691,
      "net_pnl_bps": -21351.906597263744,
      "profit_outcome_rate": 0.6987718164188752,
      "stop_outcome_rate": 0.11312217194570136,
      "trade_count": 1547,
      "vertical_outcome_rate": 0.1881060116354234
    },
    {
      "avg_abs_entry_zscore": 2.9486682086334324,
      "avg_bars_held": 3.33843085106383,
      "avg_cost_bps": 12.779440142952126,
      "avg_gross_pnl_bps": -1.5094705937722563,
      "avg_net_pnl_bps": -14.28891073672438,
      "bucket": "ADAUSDT/SOLUSDT",
      "gross_pnl_bps": -2270.2437730334736,
      "gross_profit_factor": 0.9751364671086031,
      "hit_rate_gross": 0.6123670212765957,
      "net_pnl_bps": -21490.52174803347,
      "profit_outcome_rate": 0.6868351063829787,
      "stop_outcome_rate": 0.08909574468085106,
      "trade_count": 1504,
      "vertical_outcome_rate": 0.22406914893617022
    },
    {
      "avg_abs_entry_zscore": 2.929653037680752,
      "avg_bars_held": 4.051230871590153,
      "avg_cost_bps": 13.012807717897537,
      "avg_gross_pnl_bps": -1.6817853357798889,
      "avg_net_pnl_bps": -14.694593053677425,
      "bucket": "ADAUSDT/LINKUSDT",
      "gross_pnl_bps": -2527.723359677173,
      "gross_profit_factor": 0.9723836709687912,
      "hit_rate_gross": 0.6127744510978044,
      "net_pnl_bps": -22085.97335967717,
      "profit_outcome_rate": 0.7065868263473054,
      "stop_outcome_rate": 0.11842980705256155,
      "trade_count": 1503,
      "vertical_outcome_rate": 0.17498336660013306
    },
    {
      "avg_abs_entry_zscore": 2.966534810402248,
      "avg_bars_held": 3.9244791666666665,
      "avg_cost_bps": 12.981119791666666,
      "avg_gross_pnl_bps": -1.7067470880164457,
      "avg_net_pnl_bps": -14.687866879683114,
      "bucket": "ARBUSDT/AVAXUSDT",
      "gross_pnl_bps": -2621.5635271932606,
      "gross_profit_factor": 0.9748442391367742,
      "hit_rate_gross": 0.6171875,
      "net_pnl_bps": -22560.563527193262,
      "profit_outcome_rate": 0.7005208333333334,
      "stop_outcome_rate": 0.109375,
      "trade_count": 1536,
      "vertical_outcome_rate": 0.19010416666666666
    },
    {
      "avg_abs_entry_zscore": 3.0280993477369704,
      "avg_bars_held": 4.76199494949495,
      "avg_cost_bps": 13.00811433080808,
      "avg_gross_pnl_bps": -2.217397711459939,
      "avg_net_pnl_bps": -15.225512042268019,
      "bucket": "ETHUSDT/UNIUSDT",
      "gross_pnl_bps": -3512.3579749525434,
      "gross_profit_factor": 0.953307334113671,
      "hit_rate_gross": 0.5858585858585859,
      "net_pnl_bps": -24117.211074952542,
      "profit_outcome_rate": 0.6654040404040404,
      "stop_outcome_rate": 0.10037878787878787,
      "trade_count": 1584,
      "vertical_outcome_rate": 0.2342171717171717
    },
    {
      "avg_abs_entry_zscore": 2.966911681535009,
      "avg_bars_held": 4.3305573350416395,
      "avg_cost_bps": 13.051351057014735,
      "avg_gross_pnl_bps": -3.046364377000193,
      "avg_net_pnl_bps": -16.097715434014926,
      "bucket": "ADAUSDT/DOGEUSDT",
      "gross_pnl_bps": -4755.374792497301,
      "gross_profit_factor": 0.9527039189813246,
      "hit_rate_gross": 0.6143497757847534,
      "net_pnl_bps": -25128.5337924973,
      "profit_outcome_rate": 0.6944266495836002,
      "stop_outcome_rate": 0.1133888532991672,
      "trade_count": 1561,
      "vertical_outcome_rate": 0.19218449711723254
    },
    {
      "avg_abs_entry_zscore": 2.967020607654476,
      "avg_bars_held": 4.144611186903138,
      "avg_cost_bps": 13.036152796725785,
      "avg_gross_pnl_bps": -3.8593757249398295,
      "avg_net_pnl_bps": -16.895528521665614,
      "bucket": "ARBUSDT/LINKUSDT",
      "gross_pnl_bps": -5657.84481276179,
      "gross_profit_factor": 0.9432117333097754,
      "hit_rate_gross": 0.5961800818553888,
      "net_pnl_bps": -24768.844812761792,
      "profit_outcome_rate": 0.6957708049113234,
      "stop_outcome_rate": 0.12005457025920874,
      "trade_count": 1466,
      "vertical_outcome_rate": 0.18417462482946795
    },
    {
      "avg_abs_entry_zscore": 2.9639107897575947,
      "avg_bars_held": 2.511204481792717,
      "avg_cost_bps": 12.531621988795516,
      "avg_gross_pnl_bps": -3.8865217722993517,
      "avg_net_pnl_bps": -16.418143761094868,
      "bucket": "DOTUSDT/ETHUSDT",
      "gross_pnl_bps": -5549.9530908434745,
      "gross_profit_factor": 0.9230944191264053,
      "hit_rate_gross": 0.6043417366946778,
      "net_pnl_bps": -23445.109290843473,
      "profit_outcome_rate": 0.7128851540616247,
      "stop_outcome_rate": 0.0700280112044818,
      "trade_count": 1428,
      "vertical_outcome_rate": 0.21708683473389356
    },
    {
      "avg_abs_entry_zscore": 2.907291996522837,
      "avg_bars_held": 4.0638297872340425,
      "avg_cost_bps": 13.01595744680851,
      "avg_gross_pnl_bps": -4.816151486698096,
      "avg_net_pnl_bps": -17.832108933506603,
      "bucket": "AVAXUSDT/ETCUSDT",
      "gross_pnl_bps": -7696.210075743556,
      "gross_profit_factor": 0.9302281479914883,
      "hit_rate_gross": 0.6151439299123905,
      "net_pnl_bps": -28495.710075743555,
      "profit_outcome_rate": 0.7021276595744681,
      "stop_outcome_rate": 0.10450563204005006,
      "trade_count": 1598,
      "vertical_outcome_rate": 0.19336670838548184
    },
    {
      "avg_abs_entry_zscore": 2.961235058476163,
      "avg_bars_held": 4.667721518987341,
      "avg_cost_bps": 13.166930379746836,
      "avg_gross_pnl_bps": -7.017949609097547,
      "avg_net_pnl_bps": -20.184879988844386,
      "bucket": "ETCUSDT/OPUSDT",
      "gross_pnl_bps": -11088.360382374125,
      "gross_profit_factor": 0.8945572988894883,
      "hit_rate_gross": 0.5905063291139241,
      "net_pnl_bps": -31892.11038237413,
      "profit_outcome_rate": 0.6481012658227848,
      "stop_outcome_rate": 0.1360759493670886,
      "trade_count": 1580,
      "vertical_outcome_rate": 0.2158227848101266
    },
    {
      "avg_abs_entry_zscore": 2.9581303499024116,
      "avg_bars_held": 2.5734989648033126,
      "avg_cost_bps": 12.544809730848861,
      "avg_gross_pnl_bps": -7.046586915452716,
      "avg_net_pnl_bps": -19.59139664630158,
      "bucket": "AVAXUSDT/ETHUSDT",
      "gross_pnl_bps": -10210.504440490986,
      "gross_profit_factor": 0.8806716426941493,
      "hit_rate_gross": 0.587991718426501,
      "net_pnl_bps": -28387.933740490986,
      "profit_outcome_rate": 0.6549344375431332,
      "stop_outcome_rate": 0.08281573498964803,
      "trade_count": 1449,
      "vertical_outcome_rate": 0.26224982746721875
    },
    {
      "avg_abs_entry_zscore": 2.873590906734882,
      "avg_bars_held": 4.656189865298268,
      "avg_cost_bps": 13.164047466324567,
      "avg_gross_pnl_bps": -7.078476043357573,
      "avg_net_pnl_bps": -20.242523509682137,
      "bucket": "ADAUSDT/ATOMUSDT",
      "gross_pnl_bps": -11035.344151594456,
      "gross_profit_factor": 0.8941035850603387,
      "hit_rate_gross": 0.5881975625400898,
      "net_pnl_bps": -31558.09415159445,
      "profit_outcome_rate": 0.6856959589480436,
      "stop_outcome_rate": 0.10968569595894805,
      "trade_count": 1559,
      "vertical_outcome_rate": 0.20461834509300833
    },
    {
      "avg_abs_entry_zscore": 3.0341632849121734,
      "avg_bars_held": 3.5705920624593364,
      "avg_cost_bps": 12.6968903057905,
      "avg_gross_pnl_bps": -7.3188009316646125,
      "avg_net_pnl_bps": -20.015691237455112,
      "bucket": "ETHUSDT/SOLUSDT",
      "gross_pnl_bps": -11248.997031968509,
      "gross_profit_factor": 0.8387005865578114,
      "hit_rate_gross": 0.5712426805465192,
      "net_pnl_bps": -30764.11743196851,
      "profit_outcome_rate": 0.6636304489264802,
      "stop_outcome_rate": 0.0826284970722186,
      "trade_count": 1537,
      "vertical_outcome_rate": 0.25374105400130126
    },
    {
      "avg_abs_entry_zscore": 2.931366656258328,
      "avg_bars_held": 5.307405102675793,
      "avg_cost_bps": 13.123577660236466,
      "avg_gross_pnl_bps": -10.926697671319289,
      "avg_net_pnl_bps": -24.050275331555753,
      "bucket": "ETHUSDT/OPUSDT",
      "gross_pnl_bps": -17559.203157810098,
      "gross_profit_factor": 0.8108190261037179,
      "hit_rate_gross": 0.5544492843808339,
      "net_pnl_bps": -38648.792457810094,
      "profit_outcome_rate": 0.6645924082140635,
      "stop_outcome_rate": 0.10827629122588675,
      "trade_count": 1607,
      "vertical_outcome_rate": 0.2271313005600498
    },
    {
      "avg_abs_entry_zscore": 2.9193581395758215,
      "avg_bars_held": 4.7786211258697024,
      "avg_cost_bps": 13.194655281467426,
      "avg_gross_pnl_bps": -12.67614848782701,
      "avg_net_pnl_bps": -25.870803769294433,
      "bucket": "ADAUSDT/ARBUSDT",
      "gross_pnl_bps": -20040.990759254502,
      "gross_profit_factor": 0.8260926711719283,
      "hit_rate_gross": 0.5774826059456041,
      "net_pnl_bps": -40901.7407592545,
      "profit_outcome_rate": 0.6793168880455408,
      "stop_outcome_rate": 0.13345983554712207,
      "trade_count": 1581,
      "vertical_outcome_rate": 0.18722327640733713
    },
    {
      "avg_abs_entry_zscore": 2.9193028914634165,
      "avg_bars_held": 4.918287937743191,
      "avg_cost_bps": 13.229571984435797,
      "avg_gross_pnl_bps": -14.76679529390889,
      "avg_net_pnl_bps": -27.996367278344685,
      "bucket": "DOTUSDT/OPUSDT",
      "gross_pnl_bps": -22770.398343207507,
      "gross_profit_factor": 0.7999367806127816,
      "hit_rate_gross": 0.5933852140077821,
      "net_pnl_bps": -43170.398343207504,
      "profit_outcome_rate": 0.6997405966277561,
      "stop_outcome_rate": 0.12710765239948119,
      "trade_count": 1542,
      "vertical_outcome_rate": 0.17315175097276264
    },
    {
      "avg_abs_entry_zscore": 2.9073502208084845,
      "avg_bars_held": 5.036375239310785,
      "avg_cost_bps": 13.259093809827696,
      "avg_gross_pnl_bps": -15.512493031921219,
      "avg_net_pnl_bps": -28.77158684174892,
      "bucket": "ADAUSDT/XRPUSDT",
      "gross_pnl_bps": -24308.07658102055,
      "gross_profit_factor": 0.8061524961666481,
      "hit_rate_gross": 0.5909380982769623,
      "net_pnl_bps": -45085.076581020556,
      "profit_outcome_rate": 0.6790044671346522,
      "stop_outcome_rate": 0.12699425654116145,
      "trade_count": 1567,
      "vertical_outcome_rate": 0.19400127632418634
    },
    {
      "avg_abs_entry_zscore": 2.956010220436595,
      "avg_bars_held": 4.628272251308901,
      "avg_cost_bps": 12.979805235602091,
      "avg_gross_pnl_bps": -17.133045608224197,
      "avg_net_pnl_bps": -30.11285084382629,
      "bucket": "ETHUSDT/LINKUSDT",
      "gross_pnl_bps": -26179.293689366576,
      "gross_profit_factor": 0.6723341680152952,
      "hit_rate_gross": 0.5484293193717278,
      "net_pnl_bps": -46012.43608936657,
      "profit_outcome_rate": 0.6341623036649214,
      "stop_outcome_rate": 0.10863874345549739,
      "trade_count": 1528,
      "vertical_outcome_rate": 0.25719895287958117
    }
  ],
  "side_summary": [
    {
      "avg_abs_entry_zscore": 2.9013659996086347,
      "avg_bars_held": 4.021903610295388,
      "avg_cost_bps": 12.954125838443602,
      "avg_gross_pnl_bps": 0.7236231748434003,
      "avg_net_pnl_bps": -12.2305026636002,
      "bucket": "LONG_SPREAD",
      "gross_pnl_bps": 20945.272795842222,
      "gross_profit_factor": 1.0134757551319251,
      "hit_rate_gross": 0.6043185351528761,
      "net_pnl_bps": -354011.8995979078,
      "profit_outcome_rate": 0.6879599239937814,
      "stop_outcome_rate": 0.09276213508377958,
      "trade_count": 28945,
      "vertical_outcome_rate": 0.2192779409224391
    },
    {
      "avg_abs_entry_zscore": 2.99241108574417,
      "avg_bars_held": 3.890549023074883,
      "avg_cost_bps": 12.927503850418471,
      "avg_gross_pnl_bps": -2.039115310077476,
      "avg_net_pnl_bps": -14.966619160495947,
      "bucket": "SHORT_SPREAD",
      "gross_pnl_bps": -69193.29981685898,
      "gross_profit_factor": 0.9662675461649994,
      "hit_rate_gross": 0.6078154009371408,
      "net_pnl_bps": -507862.287973109,
      "profit_outcome_rate": 0.6905961748150767,
      "stop_outcome_rate": 0.11269265906344857,
      "trade_count": 33933,
      "vertical_outcome_rate": 0.19671116612147468
    }
  ],
  "source": "sprint8_canonical_backtest_results",
  "top_gross_pairs": [
    {
      "avg_abs_entry_zscore": 2.987824338236814,
      "avg_bars_held": 3.2116585704371965,
      "avg_cost_bps": 12.780493251214436,
      "avg_gross_pnl_bps": 10.760693774039392,
      "avg_net_pnl_bps": -2.019799477175043,
      "bucket": "ETCUSDT/LTCUSDT",
      "gross_pnl_bps": 15506.159728390765,
      "gross_profit_factor": 1.2373885129038764,
      "hit_rate_gross": 0.6391394864677308,
      "net_pnl_bps": -2910.531046609237,
      "profit_outcome_rate": 0.6613462873004857,
      "stop_outcome_rate": 0.08605135322692574,
      "trade_count": 1441,
      "vertical_outcome_rate": 0.25260235947258847
    },
    {
      "avg_abs_entry_zscore": 2.836694221137136,
      "avg_bars_held": 4.497797356828194,
      "avg_cost_bps": 13.124449339207048,
      "avg_gross_pnl_bps": 9.022161129354068,
      "avg_net_pnl_bps": -4.10228820985298,
      "bucket": "AVAXUSDT/DOTUSDT",
      "gross_pnl_bps": 14336.214034543613,
      "gross_profit_factor": 1.1598021746045348,
      "hit_rate_gross": 0.6337319068596602,
      "net_pnl_bps": -6518.535965456385,
      "profit_outcome_rate": 0.7035871617369415,
      "stop_outcome_rate": 0.10258023914411579,
      "trade_count": 1589,
      "vertical_outcome_rate": 0.19383259911894274
    },
    {
      "avg_abs_entry_zscore": 2.8834858614155796,
      "avg_bars_held": 4.7902408111533585,
      "avg_cost_bps": 13.19756020278834,
      "avg_gross_pnl_bps": 8.679069943074984,
      "avg_net_pnl_bps": -4.518490259713356,
      "bucket": "ARBUSDT/OPUSDT",
      "gross_pnl_bps": 13695.572370172325,
      "gross_profit_factor": 1.159321074656414,
      "hit_rate_gross": 0.6166032953105196,
      "net_pnl_bps": -7130.1776298276745,
      "profit_outcome_rate": 0.6977186311787072,
      "stop_outcome_rate": 0.10202788339670468,
      "trade_count": 1578,
      "vertical_outcome_rate": 0.2002534854245881
    },
    {
      "avg_abs_entry_zscore": 2.857530247487126,
      "avg_bars_held": 4.573613766730402,
      "avg_cost_bps": 13.1434034416826,
      "avg_gross_pnl_bps": 8.563050089263152,
      "avg_net_pnl_bps": -4.580353352419448,
      "bucket": "ADAUSDT/DOTUSDT",
      "gross_pnl_bps": 13435.425590053885,
      "gross_profit_factor": 1.1654214287004483,
      "hit_rate_gross": 0.6175908221797323,
      "net_pnl_bps": -7186.574409946114,
      "profit_outcome_rate": 0.715742511153601,
      "stop_outcome_rate": 0.09369024856596558,
      "trade_count": 1569,
      "vertical_outcome_rate": 0.1905672402804334
    },
    {
      "avg_abs_entry_zscore": 2.8913769140754826,
      "avg_bars_held": 4.484713375796178,
      "avg_cost_bps": 13.121178343949044,
      "avg_gross_pnl_bps": 8.47997480996526,
      "avg_net_pnl_bps": -4.641203533983783,
      "bucket": "ARBUSDT/ATOMUSDT",
      "gross_pnl_bps": 13313.560451645459,
      "gross_profit_factor": 1.131861187155258,
      "hit_rate_gross": 0.6070063694267516,
      "net_pnl_bps": -7286.68954835454,
      "profit_outcome_rate": 0.7114649681528662,
      "stop_outcome_rate": 0.12165605095541401,
      "trade_count": 1570,
      "vertical_outcome_rate": 0.16687898089171974
    },
    {
      "avg_abs_entry_zscore": 2.9648829261591003,
      "avg_bars_held": 3.9654947916666665,
      "avg_cost_bps": 12.991373697916666,
      "avg_gross_pnl_bps": 8.468239939784217,
      "avg_net_pnl_bps": -4.523133758132448,
      "bucket": "ARBUSDT/ETCUSDT",
      "gross_pnl_bps": 13007.216547508557,
      "gross_profit_factor": 1.1433366465066794,
      "hit_rate_gross": 0.6204427083333334,
      "net_pnl_bps": -6947.533452491441,
      "profit_outcome_rate": 0.6985677083333334,
      "stop_outcome_rate": 0.10611979166666667,
      "trade_count": 1536,
      "vertical_outcome_rate": 0.1953125
    },
    {
      "avg_abs_entry_zscore": 3.0722743654284326,
      "avg_bars_held": 3.8105867346938775,
      "avg_cost_bps": 12.925115194515307,
      "avg_gross_pnl_bps": 7.263314477602812,
      "avg_net_pnl_bps": -5.661800716912492,
      "bucket": "DOGEUSDT/ETCUSDT",
      "gross_pnl_bps": 11388.87710088121,
      "gross_profit_factor": 1.1163118837332997,
      "hit_rate_gross": 0.6320153061224489,
      "net_pnl_bps": -8877.703524118788,
      "profit_outcome_rate": 0.6964285714285714,
      "stop_outcome_rate": 0.10522959183673469,
      "trade_count": 1568,
      "vertical_outcome_rate": 0.19834183673469388
    },
    {
      "avg_abs_entry_zscore": 2.9896181583914587,
      "avg_bars_held": 4.406423718344657,
      "avg_cost_bps": 13.069769518221126,
      "avg_gross_pnl_bps": 7.236557070049314,
      "avg_net_pnl_bps": -5.833212448171807,
      "bucket": "DOGEUSDT/DOTUSDT",
      "gross_pnl_bps": 11715.98589640984,
      "gross_profit_factor": 1.1088720182584149,
      "hit_rate_gross": 0.6287831995058678,
      "net_pnl_bps": -9443.970953590155,
      "profit_outcome_rate": 0.7103150092649784,
      "stop_outcome_rate": 0.11982705373687462,
      "trade_count": 1619,
      "vertical_outcome_rate": 0.169857936998147
    },
    {
      "avg_abs_entry_zscore": 2.8341085231965897,
      "avg_bars_held": 4.542664211172498,
      "avg_cost_bps": 13.135666052793125,
      "avg_gross_pnl_bps": 4.93067724146818,
      "avg_net_pnl_bps": -8.204988811324945,
      "bucket": "ATOMUSDT/DOTUSDT",
      "gross_pnl_bps": 8032.073226351665,
      "gross_profit_factor": 1.1006086262152561,
      "hit_rate_gross": 0.6193984039287906,
      "net_pnl_bps": -13365.926773648334,
      "profit_outcome_rate": 0.6942909760589319,
      "stop_outcome_rate": 0.1092694904849601,
      "trade_count": 1629,
      "vertical_outcome_rate": 0.19643953345610804
    },
    {
      "avg_abs_entry_zscore": 2.9289988266451275,
      "avg_bars_held": 4.547099189020586,
      "avg_cost_bps": 13.136774797255146,
      "avg_gross_pnl_bps": 4.347401749392494,
      "avg_net_pnl_bps": -8.78937304786265,
      "bucket": "ARBUSDT/DOTUSDT",
      "gross_pnl_bps": 6968.885004276169,
      "gross_profit_factor": 1.068496420573064,
      "hit_rate_gross": 0.6138490330630069,
      "net_pnl_bps": -14089.364995723829,
      "profit_outcome_rate": 0.7105427323767936,
      "stop_outcome_rate": 0.11977542108546475,
      "trade_count": 1603,
      "vertical_outcome_rate": 0.16968184653774174
    }
  ],
  "trade_count": 62878
}